chi/__init__.py
chi/clients.py
chi/container.py
chi/context.py
chi/exception.py
chi/hardware.py
chi/image.py
chi/jupyterhub.py
chi/keypair.py
chi/lease.py
chi/magic.py
chi/network.py
chi/server.py
chi/share.py
chi/ssh.py
chi/storage.py
chi/util.py
python_chi-1.2.6.dist-info/licenses/AUTHORS
python_chi-1.2.6.dist-info/licenses/LICENSE
python_chi-1.2.6.dist-info/METADATA
python_chi-1.2.6.dist-info/WHEEL
python_chi-1.2.6.dist-info/dependency_links.txt
python_chi-1.2.6.dist-info/pbr.json
python_chi-1.2.6.dist-info/top_level.txt
python_chi-1.2.6.dist-info/RECORD
